rusty_orbital_dynamics-0.1.0.dist-info/METADATA
rusty_orbital_dynamics-0.1.0.dist-info/WHEEL
rusty_orbital_dynamics-0.1.0.dist-info/licenses/LICENSE
rusty_orbital_dynamics/helpers.py
rusty_orbital_dynamics/__init__.py
rusty_orbital_dynamics/rusty_orbital_dynamics.cpython-312-x86_64-linux-gnu.so
rusty_orbital_dynamics-0.1.0.dist-info/RECORD
