Metadata-Version: 2.4
Name: rusty_orbital_dynamics
Version: 0.1.0
License-File: LICENSE
Summary: High-performance orbital dynamics in Rust + Python
Keywords: orbital,dynamics,python
Author: Jacob Sorensen <sorensenjacob44@gmail.com>
Author-email: Jacob Sorensen <sorensenjacob44@gmail.com>
License: GPL-3.0-or-later
Project-URL: Source Code, https://github.com/JacobASorensen/rusty-orbital-dynamics
